[
  {
    "gtin": "8904159162031",
    "registrationNo": "Rwanda FDA-HMP-MA-0033",
    "productBrandName": "ILET B2",
    "genericName": "Glimepiride, Metformin HCl",
    "dosageStrength": "2mg, 500mg",
    "dosageForm": "Tablets",
    "packSize": "Box Of 10, Box Of 30",
    "packagingType": "ALU-PVC/PVDC BLISTER PACK",
    "shelfLife": "24 Months",
    "manufacturerName": "MSN LABORATORIES PRIVATE LIMITED (Formulations Division)",
    "manufacturerCountry": "India",
    "marketingAuthorizationHolder": "MSN LABORATORIES PRIVATE LIMITED",
    "localTechnicalRepresentative": "ABACUS PHARMA (A) LTD",
    "registrationDate": "2020-09-07",
    "expiryDate": "2025-09-07"
  },
  {
    "gtin": "3760021453019",
    "registrationNo": "Rwanda FDA-HMP-MA-0021",
    "productBrandName": "BI-PRETERAX",
    "genericName": "Peridopril Arginine, Indapamide",
    "dosageStrength": "5mg, 1.25mg",
    "dosageForm": "Tablets",
    "packSize": "30 Film Coated Tablets",
    "packagingType": "POLYPROPYLENE CONTAINER",
    "shelfLife": "36 Months",
    "manufacturerName": "LES LABORATOIRES SERVIER",
    "manufacturerCountry": "France",
    "marketingAuthorizationHolder": "LES LABORATOIRES SERVIER",
    "localTechnicalRepresentative": "KIPHARMA LTD",
    "registrationDate": "2020-09-15",
    "expiryDate": "2025-09-15"
  },
  {
    "gtin": "3760021453026",
    "registrationNo": "Rwanda FDA-HMP-MA-0022",
    "productBrandName": "DIAMICRON MR",
    "genericName": "Gliclazide",
    "dosageStrength": "60mg",
    "dosageForm": "Tablets",
    "packSize": "30 Film Coated Tablets",
    "packagingType": "ALU-ALU BLISTER PACK",
    "shelfLife": "24 Months",
    "manufacturerName": "LES LABORATOIRES SERVIER",
    "manufacturerCountry": "France",
    "marketingAuthorizationHolder": "LES LABORATOIRES SERVIER",
    "localTechnicalRepresentative": "KIPHARMA LTD",
    "registrationDate": "2020-09-15",
    "expiryDate": "2025-09-15"
  },
  {
    "gtin": "0365001128794",
    "registrationNo": "Rwanda FDA-HMP-MA-0023",
    "productBrandName": "EYLEA",
    "genericName": "Aflibercept",
    "dosageStrength": "40mg/ml",
    "dosageForm": "Solution For Injection",
    "packSize": "1 Vial*2ml",
    "packagingType": "TYPE 1 GLASS VIAL",
    "shelfLife": "24 Months",
    "manufacturerName": "RAGENERON PHARMACEUTICALS / BAYER AG / VETTER PHARMA-FERTIGUNG GMBH & CO",
    "manufacturerCountry": "USA, Germany",
    "marketingAuthorizationHolder": "BAYER EAST AFRICA LIMITED",
    "localTechnicalRepresentative": "SURGIPHARM (RWANDA) LTD",
    "registrationDate": "2020-09-15",
    "expiryDate": "2025-09-15"
  },
  {
    "gtin": "8904159162147",
    "registrationNo": "Rwanda FDA-HMP-MA-0024",
    "productBrandName": "FLOXSAFE-400",
    "genericName": "Moxifloxacin",
    "dosageStrength": "400mg",
    "dosageForm": "Tablets",
    "packSize": "3 Blisters Of 5 Tablets",
    "packagingType": "PVC /PVDC BLISTER PACK",
    "shelfLife": "24 Months",
    "manufacturerName": "MSN LABORATORIES PRIVATE LIMITED (Formulations Division)",
    "manufacturerCountry": "India",
    "marketingAuthorizationHolder": "MSN LABORATORIES PRIVATE LIMITED",
    "localTechnicalRepresentative": "ABACUS PHARMA (A) LTD",
    "registrationDate": "2020-09-15",
    "expiryDate": "2025-09-15"
  },
  {
    "gtin": "8904159162154",
    "registrationNo": "Rwanda FDA-HMP-MA-0025",
    "productBrandName": "LDNIL-5",
    "genericName": "Rosuvastatin",
    "dosageStrength": "5mg",
    "dosageForm": "Tablets",
    "packSize": "3*10 Blister Pack",
    "packagingType": "ALU BLISTER PACK",
    "shelfLife": "24 Months",
    "manufacturerName": "MSN LABORATORIES PRIVATE LIMITED (Formulations Division)",
    "manufacturerCountry": "India",
    "marketingAuthorizationHolder": "MSN LABORATORIES PRIVATE LIMITED",
    "localTechnicalRepresentative": "ABACUS PHARMA (A) LTD",
    "registrationDate": "2020-09-15",
    "expiryDate": "2025-09-15"
  },
  {
    "gtin": "8904159162161",
    "registrationNo": "Rwanda FDA-HMP-MA-0026",
    "productBrandName": "LDNIL-10",
    "genericName": "Rosuvastatin",
    "dosageStrength": "10mg",
    "dosageForm": "Tablets",
    "packSize": "3*10 Blister Pack",
    "packagingType": "ALU BLISTER PACK",
    "shelfLife": "24 Months",
    "manufacturerName": "MSN LABORATORIES PRIVATE LIMITED (Formulations Division)",
    "manufacturerCountry": "India",
    "marketingAuthorizationHolder": "MSN LABORATORIES PRIVATE LIMITED",
    "localTechnicalRepresentative": "ABACUS PHARMA (A) LTD",
    "registrationDate": "2020-09-15",
    "expiryDate": "2025-09-15"
  },
  {
    "gtin": "8904159162178",
    "registrationNo": "Rwanda FDA-HMP-MA-0027",
    "productBrandName": "PREGASAFE-75",
    "genericName": "Pregabalin",
    "dosageStrength": "75mg",
    "dosageForm": "Capsules",
    "packSize": "10 Capsules Blister Pack",
    "packagingType": "ALU PVC/PVDC BLISTER PACK",
    "shelfLife": "24 Months",
    "manufacturerName": "MSN LABORATORIES PRIVATE LIMITED (Formulations Division)",
    "manufacturerCountry": "India",
    "marketingAuthorizationHolder": "MSN LABORATORIES PRIVATE LIMITED",
    "localTechnicalRepresentative": "ABACUS PHARMA (A) LTD",
    "registrationDate": "2020-09-15",
    "expiryDate": "2025-09-15"
  },
  {
    "gtin": "0365001128800",
    "registrationNo": "Rwanda FDA-HMP-MA-0028",
    "productBrandName": "SURVANTA",
    "genericName": "Beractant",
    "dosageStrength": "25mg/ml",
    "dosageForm": "Suspension",
    "packSize": "4ml & 8ml",
    "packagingType": "USP TYPE 1 GLASS",
    "shelfLife": "18 Months",
    "manufacturerName": "ABBVIE (PTY) Ltd",
    "manufacturerCountry": "USA",
    "marketingAuthorizationHolder": "ABBVIE(PTY) LTD",
    "localTechnicalRepresentative": "PRAFIN RWANDA LTD",
    "registrationDate": "2020-09-15",
    "expiryDate": "2025-09-15"
  },
  {
    "gtin": "8904159162185",
    "registrationNo": "Rwanda FDA-HMP-MA-0029",
    "productBrandName": "ALGIC-P",
    "genericName": "Aceclofenac, Paracetamol",
    "dosageStrength": "100mg, 500mg",
    "dosageForm": "Coated Tablets",
    "packSize": "3*10 Tablets",
    "packagingType": "ALU-PVC/PVDC BLISTER PACK",
    "shelfLife": "24 Months",
    "manufacturerName": "MSN LABORATORIES PRIVATE LIMITED (Formulations Division)",
    "manufacturerCountry": "India",
    "marketingAuthorizationHolder": "MSN LABORATORIES PRIVATE LIMITED",
    "localTechnicalRepresentative": "ABACUS PHARMA (A) LTD",
    "registrationDate": "2020-09-15",
    "expiryDate": "2025-09-15"
  },
  {
    "gtin": "8904159162192",
    "registrationNo": "Rwanda FDA-HMP-MA-0030",
    "productBrandName": "ATOREM-10",
    "genericName": "Atorvastatin",
    "dosageStrength": "10mg",
    "dosageForm": "Tablets",
    "packSize": "Blister Of 10 Tablets",
    "packagingType": "ALU-ALU BLISTER PACK",
    "shelfLife": "24 Months",
    "manufacturerName": "MSN LABORATORIES PRIVATE LIMITED (Formulations Division)",
    "manufacturerCountry": "India",
    "marketingAuthorizationHolder": "MSN LABORATORIES PRIVATE LIMITED",
    "localTechnicalRepresentative": "ABACUS PHARMA (A) LTD",
    "registrationDate": "2020-09-15",
    "expiryDate": "2025-09-15"
  },
  {
    "gtin": "8904159162208",
    "registrationNo": "Rwanda FDA-HMP-MA-0031",
    "productBrandName": "ATOREM-20",
    "genericName": "Atorvastatin",
    "dosageStrength": "20mg",
    "dosageForm": "Tablets",
    "packSize": "Blister Of 10 Tablets",
    "packagingType": "ALU-ALU BLISTER PACK",
    "shelfLife": "24 Months",
    "manufacturerName": "MSN LABORATORIES PRIVATE LIMITED (Formulations Division)",
    "manufacturerCountry": "India",
    "marketingAuthorizationHolder": "MSN LABORATORIES PRIVATE LIMITED",
    "localTechnicalRepresentative": "ABACUS PHARMA (A) LTD",
    "registrationDate": "2020-09-15",
    "expiryDate": "2025-09-15"
  },
  {
    "gtin": "8904159162215",
    "registrationNo": "Rwanda FDA-HMP-MA-0032",
    "productBrandName": "ILET B1",
    "genericName": "Glimepiride, Metformin HCl",
    "dosageStrength": "1mg, 500mg",
    "dosageForm": "Tablets",
    "packSize": "Box Of 10, Box Of 30",
    "packagingType": "ALU-PVC/PVDC BLISTER PACK",
    "shelfLife": "24 Months",
    "manufacturerName": "MSN LABORATORIES PRIVATE LIMITED (Formulations Division)",
    "manufacturerCountry": "India",
    "marketingAuthorizationHolder": "MSN LABORATORIES PRIVATE LIMITED",
    "localTechnicalRepresentative": "ABACUS PHARMA (A) LTD",
    "registrationDate": "2020-09-15",
    "expiryDate": "2025-09-15"
  },
  {
    "gtin": "8904159162222",
    "registrationNo": "Rwanda FDA-HMP-MA-0034",
    "productBrandName": "RAMGIC",
    "genericName": "Tramadol HCl",
    "dosageStrength": "50mg/ml",
    "dosageForm": "Injectable",
    "packSize": "2ml Of 10 Amp.Pack /Carton",
    "packagingType": "USP TYPE 1 GLASS",
    "shelfLife": "24 Months",
    "manufacturerName": "MSN LABORATORIES PRIVATE LIMITED (Formulations Division)",
    "manufacturerCountry": "India",
    "marketingAuthorizationHolder": "MSN LABORATORIES PRIVATE LIMITED",
    "localTechnicalRepresentative": "ABACUS PHARMA (A) LTD",
    "registrationDate": "2020-09-15",
    "expiryDate": "2025-09-15"
  },
  {
    "gtin": "8904159162239",
    "registrationNo": "Rwanda FDA-HMP-MA-0035",
    "productBrandName": "SAFELEVO-750",
    "genericName": "Levofloxacin",
    "dosageStrength": "750mg",
    "dosageForm": "Tablets",
    "packSize": "Box Of 10, Box Of 30",
    "packagingType": "ALU-PVC/PVDC PACK",
    "shelfLife": "36 Months",
    "manufacturerName": "MSN LABORATORIES PRIVATE LIMITED (Formulations Division)",
    "manufacturerCountry": "India",
    "marketingAuthorizationHolder": "MSN LABORATORIES PRIVATE LIMITED",
    "localTechnicalRepresentative": "ABACUS PHARMA (A) LTD",
    "registrationDate": "2020-09-15",
    "expiryDate": "2025-09-15"
  }
]
